LICENSE
MANIFEST.in
README.rst
setup.cfg
setup.py
online_test/__init__.py
online_test/settings.py
online_test/test_settings.py
online_test/urls.py
online_test/wsgi.py
yaksh/__init__.py
yaksh/admin.py
yaksh/base_evaluator.py
yaksh/bash_code_evaluator.py
yaksh/bash_stdio_evaluator.py
yaksh/code_server.py
yaksh/cpp_code_evaluator.py
yaksh/cpp_stdio_evaluator.py
yaksh/decorators.py
yaksh/error_messages.py
yaksh/file_utils.py
yaksh/forms.py
yaksh/grader.py
yaksh/hook_evaluator.py
yaksh/java_code_evaluator.py
yaksh/java_stdio_evaluator.py
yaksh/language_registry.py
yaksh/models.py
yaksh/python_assertion_evaluator.py
yaksh/python_stdio_evaluator.py
yaksh/scilab_code_evaluator.py
yaksh/send_emails.py
yaksh/settings.py
yaksh/stdio_evaluator.py
yaksh/test_models.py
yaksh/test_views.py
yaksh/urls.py
yaksh/urls_password_reset.py
yaksh/views.py
yaksh.egg-info/PKG-INFO
yaksh.egg-info/SOURCES.txt
yaksh.egg-info/dependency_links.txt
yaksh.egg-info/entry_points.txt
yaksh.egg-info/requires.txt
yaksh.egg-info/top_level.txt
yaksh/demo_templates/demo_settings.py
yaksh/demo_templates/demo_urls.py
yaksh/docs/sample.args
yaksh/docs/sample.sh
yaksh/docs/sample_questions.py
yaksh/docs/sample_questions.xml
yaksh/evaluator_tests/__init__.py
yaksh/evaluator_tests/test_bash_evaluation.py
yaksh/evaluator_tests/test_c_cpp_evaluation.py
yaksh/evaluator_tests/test_grader_evaluation.py
yaksh/evaluator_tests/test_java_evaluation.py
yaksh/evaluator_tests/test_python_evaluation.py
yaksh/evaluator_tests/test_python_stdio_evaluator.py
yaksh/evaluator_tests/test_scilab_evaluation.py
yaksh/evaluator_tests/test_simple_question_types.py
yaksh/fixtures/demo_fixtures.json
yaksh/fixtures/demo_questions.zip
yaksh/fixtures/sample_user_upload.csv
yaksh/fixtures/users_add_update_reject.csv
yaksh/fixtures/users_correct.csv
yaksh/fixtures/users_some_headers_missing.csv
yaksh/fixtures/users_some_values_missing.csv
yaksh/fixtures/users_with_no_values.csv
yaksh/live_server_tests/__init__.py
yaksh/live_server_tests/load_test.py
yaksh/live_server_tests/selenium_test.py
yaksh/management/__init__.py
yaksh/management/__init__.pyc
yaksh/management/__pycache__/__init__.cpython-35.pyc
